beam/__init__.py
beam/views.py
beam/viewsets.py
beam/templatetags/__init__.py
beam/templatetags/beam_tags.py
beam/themes/__init__.py
beam/themes/bootstrap4/__init__.py
beam/themes/bootstrap4/templates/beam/base.html
beam/themes/bootstrap4/templates/beam/create.html
beam/themes/bootstrap4/templates/beam/delete.html
beam/themes/bootstrap4/templates/beam/detail.html
beam/themes/bootstrap4/templates/beam/list.html
beam/themes/bootstrap4/templates/beam/update.html
beam/themes/bootstrap4/templates/beam/partials/links.html
beam/themes/plain/__init__.py
beam/themes/plain/templates/beam/base.html
beam/themes/plain/templates/beam/create.html
beam/themes/plain/templates/beam/delete.html
beam/themes/plain/templates/beam/detail.html
beam/themes/plain/templates/beam/list.html
beam/themes/plain/templates/beam/update.html
beam/themes/plain/templates/beam/partials/links.html
django_beam-0.0.5.dist-info/METADATA
django_beam-0.0.5.dist-info/RECORD
django_beam-0.0.5.dist-info/WHEEL
django_beam-0.0.5.dist-info/top_level.txt
