Metadata-Version: 2.1
Name: django-beam
Version: 0.0.5
Summary: A crud library for python
Home-page: https://github.com/django-beam/django-beam
Author: Raphael Kimmig
Author-email: raphael@ampad.de
License: BSD 3-Clause License
Download-URL: https://github.com/django-beam/django-beam/archive/0.0.5.tar.gz
Platform: UNKNOWN
Classifier: Framework :: Django
Classifier: Programming Language :: Python :: 3
Requires-Dist: django (~=2.0)
Requires-Dist: django-crispy-forms (~=1.7)
